{"v":"5.10.0","fr":30,"ip":0,"op":90,"w":350,"h":350,"nm":"Flower_Lottie","ddd":0,"assets":[{"id":"comp_0","nm":"grey","fr":30,"layers":[{"ddd":0,"ind":1,"ty":4,"nm":"Isolation Mode","sr":1,"ks":{"o":{"a":0,"k":100,"ix":11},"r":{"a":0,"k":0,"ix":10},"p":{"a":1,"k":[{"i":{"x":0.833,"y":0.833},"o":{"x":0.167,"y":0.167},"t":0,"s":[6.096,6.566,0],"to":[4.029,-4.191,0],"ti":[4.298,-4.795,0]},{"i":{"x":0.833,"y":0.833},"o":{"x":0.167,"y":0.167},"t":45,"s":[13.721,13.191,0],"to":[-4.586,5.116,0],"ti":[-4.221,5.684,0]},{"t":89,"s":[6.096,6.566,0]}],"ix":2,"l":2},"a":{"a":0,"k":[0,0,0],"ix":1,"l":2},"s":{"a":0,"k":[100,100,100],"ix":6,"l":2}},"ao":0,"shapes":[{"ty":"gr","it":[{"ind":0,"ty":"sh","ix":1,"ks":{"a":0,"k":{"i":[[-2.652,0],[0,-2.652],[2.652,0],[0,2.652]],"o":[[2.652,0],[0,2.652],[-2.652,0],[0,-2.652]],"v":[[0,-4.804],[4.804,0],[0,4.804],[-4.804,0]],"c":true},"ix":2},"nm":"Path 1","mn":"ADBE Vector Shape - Group","hd":false},{"ty":"fl","c":{"a":0,"k":[0.843137264252,0.913725495338,0.988235294819,1],"ix":4},"o":{"a":0,"k":100,"ix":5},"r":1,"bm":0,"nm":"Fill 1","mn":"ADBE Vector Graphic - Fill","hd":false},{"ty":"tr","p":{"a":0,"k":[0,0],"ix":2},"a":{"a":0,"k":[0,0],"ix":1},"s":{"a":0,"k":[100,100],"ix":3},"r":{"a":0,"k":0,"ix":6},"o":{"a":0,"k":100,"ix":7},"sk":{"a":0,"k":0,"ix":4},"sa":{"a":0,"k":0,"ix":5},"nm":"Transform"}],"nm":"Group 1","np":2,"cix":2,"bm":0,"ix":1,"mn":"ADBE Vector Group","hd":false}],"ip":-9,"op":94,"st":0,"ct":1,"bm":0}]},{"id":"comp_1","nm":"purple","fr":30,"layers":[{"ddd":0,"ind":1,"ty":4,"nm":"Isolation Mode 6","sr":1,"ks":{"o":{"a":0,"k":100,"ix":11},"r":{"a":0,"k":0,"ix":10},"p":{"a":1,"k":[{"i":{"x":0.833,"y":0.833},"o":{"x":0.167,"y":0.167},"t":0,"s":[35.115,19.416,0],"to":[-6.49,-11.166,0],"ti":[-6.422,-12.55,0]},{"i":{"x":0.833,"y":0.833},"o":{"x":0.167,"y":0.167},"t":45,"s":[16.115,27.916,0],"to":[6.76,13.209,0],"ti":[5.072,10.272,0]},{"t":89,"s":[35.115,19.416,0]}],"ix":2,"l":2},"a":{"a":0,"k":[0,0,0],"ix":1,"l":2},"s":{"a":0,"k":[100,100,100],"ix":6,"l":2}},"ao":0,"shapes":[{"ty":"gr","it":[{"ind":0,"ty":"sh","ix":1,"ks":{"a":0,"k":{"i":[[-6.288,0],[0,-6.288],[6.288,0],[0,6.288]],"o":[[6.288,0],[0,6.288],[-6.288,0],[0,-6.288]],"v":[[0,-11.385],[11.385,0],[0,11.385],[-11.385,0]],"c":true},"ix":2},"nm":"Path 1","mn":"ADBE Vector Shape - Group","hd":false},{"ty":"fl","c":{"a":0,"k":[0.600000023842,0.588235318661,1,1],"ix":4},"o":{"a":0,"k":100,"ix":5},"r":1,"bm":0,"nm":"Fill 1","mn":"ADBE Vector Graphic - Fill","hd":false},{"ty":"tr","p":{"a":0,"k":[0,0],"ix":2},"a":{"a":0,"k":[0,0],"ix":1},"s":{"a":0,"k":[100,100],"ix":3},"r":{"a":0,"k":0,"ix":6},"o":{"a":0,"k":100,"ix":7},"sk":{"a":0,"k":0,"ix":4},"sa":{"a":0,"k":0,"ix":5},"nm":"Transform"}],"nm":"Group 1","np":2,"cix":2,"bm":0,"ix":1,"mn":"ADBE Vector Group","hd":false}],"ip":-9,"op":94,"st":0,"ct":1,"bm":0}]}],"layers":[{"ddd":0,"ind":1,"ty":4,"nm":"Isolation Mode 2","sr":1,"ks":{"o":{"a":0,"k":100,"ix":11},"r":{"a":1,"k":[{"i":{"x":[0.667],"y":[1]},"o":{"x":[0.333],"y":[0]},"t":10,"s":[0]},{"t":43,"s":[90]}],"ix":10},"p":{"a":0,"k":[175,175,0],"ix":2,"l":2},"a":{"a":0,"k":[0.07,16.187,0],"ix":1,"l":2},"s":{"a":1,"k":[{"i":{"x":[0.667,0.667,0.667],"y":[1,1,1]},"o":{"x":[0.333,0.333,0.333],"y":[0,0,0]},"t":10,"s":[100,100,100]},{"i":{"x":[0.667,0.667,0.667],"y":[1,1,1]},"o":{"x":[0.333,0.333,0.333],"y":[0,0,0]},"t":17,"s":[115,115,100]},{"i":{"x":[0.667,0.667,0.667],"y":[1,1,1]},"o":{"x":[0.333,0.333,0.333],"y":[0,0,0]},"t":25,"s":[90,90,100]},{"i":{"x":[0.667,0.667,0.667],"y":[1,1,1]},"o":{"x":[0.333,0.333,0.333],"y":[0,0,0]},"t":33,"s":[110,110,100]},{"t":43,"s":[100,100,100]}],"ix":6,"l":2}},"ao":0,"shapes":[{"ty":"gr","it":[{"ind":0,"ty":"sh","ix":1,"ks":{"a":0,"k":{"i":[[-4.369,0],[0,-4.369],[4.369,0],[0,4.369]],"o":[[4.369,0],[0,4.369],[-4.369,0],[0,-4.369]],"v":[[0.07,8.28],[7.977,16.187],[0.07,24.093],[-7.837,16.187]],"c":true},"ix":2},"nm":"Path 1","mn":"ADBE Vector Shape - Group","hd":false},{"ty":"fl","c":{"a":0,"k":[0.301960796118,0.262745112181,0.537254929543,1],"ix":4},"o":{"a":0,"k":100,"ix":5},"r":1,"bm":0,"nm":"Fill 1","mn":"ADBE Vector Graphic - Fill","hd":false},{"ty":"tr","p":{"a":0,"k":[0,0],"ix":2},"a":{"a":0,"k":[0,0],"ix":1},"s":{"a":0,"k":[100,100],"ix":3},"r":{"a":0,"k":0,"ix":6},"o":{"a":0,"k":100,"ix":7},"sk":{"a":0,"k":0,"ix":4},"sa":{"a":0,"k":0,"ix":5},"nm":"Transform"}],"nm":"Group 1","np":2,"cix":2,"bm":0,"ix":1,"mn":"ADBE Vector Group","hd":false},{"ty":"gr","it":[{"ind":0,"ty":"sh","ix":1,"ks":{"a":0,"k":{"i":[[-15.284,0],[0,-15.284],[15.284,0],[0,15.284]],"o":[[15.284,0],[0,15.284],[-15.284,0],[0,-15.284]],"v":[[0.07,-11.488],[27.745,16.187],[0.07,43.861],[-27.604,16.187]],"c":true},"ix":2},"nm":"Path 1","mn":"ADBE Vector Shape - Group","hd":false},{"ty":"fl","c":{"a":0,"k":[1,0.768627464771,0,1],"ix":4},"o":{"a":0,"k":100,"ix":5},"r":1,"bm":0,"nm":"Fill 1","mn":"ADBE Vector Graphic - Fill","hd":false},{"ty":"tr","p":{"a":0,"k":[0,0],"ix":2},"a":{"a":0,"k":[0,0],"ix":1},"s":{"a":0,"k":[100,100],"ix":3},"r":{"a":0,"k":0,"ix":6},"o":{"a":0,"k":100,"ix":7},"sk":{"a":0,"k":0,"ix":4},"sa":{"a":0,"k":0,"ix":5},"nm":"Transform"}],"nm":"Group 2","np":2,"cix":2,"bm":0,"ix":2,"mn":"ADBE Vector Group","hd":false},{"ty":"gr","it":[{"ind":0,"ty":"sh","ix":1,"ks":{"a":0,"k":{"i":[[15.071,-21.017],[0,-8.452],[25.516,-4.199],[5.978,-5.974],[21.017,15.071],[8.452,0],[4.199,25.516],[5.974,5.978],[-15.071,21.017],[0,8.452],[-25.516,4.199],[-5.978,5.974],[-21.017,-15.071],[-8.453,0],[-4.199,-25.516],[-5.974,-5.978]],"o":[[25.516,4.199],[0,8.452],[15.071,21.017],[-5.974,5.978],[-4.199,25.516],[-8.453,0],[-21.017,15.071],[-5.978,-5.974],[-25.516,-4.199],[0,-8.452],[-15.071,-21.017],[5.974,-5.978],[4.199,-25.516],[8.452,0],[21.017,-15.071],[5.978,5.974]],"v":[[48.532,-3.885],[91,16.187],[48.532,36.258],[64.366,80.482],[20.142,64.648],[0.07,107.116],[-20.001,64.648],[-64.225,80.482],[-48.391,36.258],[-90.859,16.187],[-48.391,-3.885],[-64.225,-48.109],[-20.001,-32.275],[0.07,-74.743],[20.142,-32.275],[64.366,-48.109]],"c":true},"ix":2},"nm":"Path 1","mn":"ADBE Vector Shape - Group","hd":false},{"ty":"fl","c":{"a":0,"k":[1,0.905882358551,0.415686279535,1],"ix":4},"o":{"a":0,"k":100,"ix":5},"r":1,"bm":0,"nm":"Fill 1","mn":"ADBE Vector Graphic - Fill","hd":false},{"ty":"tr","p":{"a":0,"k":[0,0],"ix":2},"a":{"a":0,"k":[0,0],"ix":1},"s":{"a":0,"k":[100,100],"ix":3},"r":{"a":0,"k":0,"ix":6},"o":{"a":0,"k":100,"ix":7},"sk":{"a":0,"k":0,"ix":4},"sa":{"a":0,"k":0,"ix":5},"nm":"Transform"}],"nm":"Group 3","np":2,"cix":2,"bm":0,"ix":3,"mn":"ADBE Vector Group","hd":false}],"ip":-15,"op":95,"st":0,"ct":1,"bm":0},{"ddd":0,"ind":2,"ty":4,"nm":"Shape Layer 3","sr":1,"ks":{"o":{"a":0,"k":100,"ix":11},"r":{"a":1,"k":[{"i":{"x":[0.833],"y":[0.833]},"o":{"x":[0.167],"y":[0.167]},"t":31,"s":[16.229]},{"i":{"x":[0.833],"y":[0.833]},"o":{"x":[0.167],"y":[0.167]},"t":36,"s":[91.784]},{"t":41,"s":[44.442]}],"ix":10},"p":{"a":1,"k":[{"i":{"x":0.833,"y":0.833},"o":{"x":0.167,"y":0.167},"t":31,"s":[147.772,244.75,0],"to":[3,51.833,0],"ti":[24,-53.583,0]},{"t":41,"s":[31.772,288.75,0]}],"ix":2,"l":2},"a":{"a":0,"k":[-93.728,-38.75,0],"ix":1,"l":2},"s":{"a":1,"k":[{"i":{"x":[0.667,0.667,0.667],"y":[1,1,1]},"o":{"x":[0.333,0.333,0.333],"y":[0,0,0]},"t":36,"s":[100,100,100]},{"t":41,"s":[0,0,100]}],"ix":6,"l":2}},"ao":0,"shapes":[{"ty":"gr","it":[{"ind":0,"ty":"sh","ix":1,"ks":{"a":0,"k":{"i":[[-12.5,13.25],[13.25,-12.75]],"o":[[11.25,11.5],[-13.25,-12.25]],"v":[[0,-21.75],[0,14.75]],"c":true},"ix":2},"nm":"Path 1","mn":"ADBE Vector Shape - Group","hd":false},{"ty":"fl","c":{"a":0,"k":[1,0.90588241278,0.415686304429,1],"ix":4},"o":{"a":0,"k":100,"ix":5},"r":1,"bm":0,"nm":"Fill 1","mn":"ADBE Vector Graphic - Fill","hd":false},{"ty":"tr","p":{"a":0,"k":[-93.5,-35.25],"ix":2},"a":{"a":0,"k":[0,0],"ix":1},"s":{"a":0,"k":[100,100],"ix":3},"r":{"a":0,"k":0,"ix":6},"o":{"a":0,"k":100,"ix":7},"sk":{"a":0,"k":0,"ix":4},"sa":{"a":0,"k":0,"ix":5},"nm":"Transform"}],"nm":"Ellipse 1","np":3,"cix":2,"bm":0,"ix":1,"mn":"ADBE Vector Group","hd":false}],"ip":31,"op":42,"st":31,"ct":1,"bm":0},{"ddd":0,"ind":3,"ty":4,"nm":"Shape Layer 1","sr":1,"ks":{"o":{"a":0,"k":100,"ix":11},"r":{"a":1,"k":[{"i":{"x":[0.833],"y":[0.833]},"o":{"x":[0.167],"y":[0.167]},"t":26,"s":[11.941]},{"i":{"x":[0.833],"y":[0.833]},"o":{"x":[0.167],"y":[0.167]},"t":31,"s":[58.834]},{"t":36,"s":[17.071]}],"ix":10},"p":{"a":1,"k":[{"i":{"x":0.833,"y":0.833},"o":{"x":0.167,"y":0.167},"t":26,"s":[225.272,128.75,0],"to":[-5.75,-43.167,0],"ti":[-2.75,55.167,0]},{"t":36,"s":[298.772,46.75,0]}],"ix":2,"l":2},"a":{"a":0,"k":[-93.728,-38.75,0],"ix":1,"l":2},"s":{"a":1,"k":[{"i":{"x":[0.667,0.667,0.667],"y":[1,1,1]},"o":{"x":[0.333,0.333,0.333],"y":[0,0,0]},"t":31,"s":[100,100,100]},{"t":36,"s":[0,0,100]}],"ix":6,"l":2}},"ao":0,"shapes":[{"ty":"gr","it":[{"ind":0,"ty":"sh","ix":1,"ks":{"a":0,"k":{"i":[[-12.5,13.25],[13.25,-12.75]],"o":[[11.25,11.5],[-13.25,-12.25]],"v":[[0,-21.75],[0,14.75]],"c":true},"ix":2},"nm":"Path 1","mn":"ADBE Vector Shape - Group","hd":false},{"ty":"fl","c":{"a":0,"k":[1,0.90588241278,0.415686304429,1],"ix":4},"o":{"a":0,"k":100,"ix":5},"r":1,"bm":0,"nm":"Fill 1","mn":"ADBE Vector Graphic - Fill","hd":false},{"ty":"tr","p":{"a":0,"k":[-93.5,-35.25],"ix":2},"a":{"a":0,"k":[0,0],"ix":1},"s":{"a":0,"k":[100,100],"ix":3},"r":{"a":0,"k":0,"ix":6},"o":{"a":0,"k":100,"ix":7},"sk":{"a":0,"k":0,"ix":4},"sa":{"a":0,"k":0,"ix":5},"nm":"Transform"}],"nm":"Ellipse 1","np":3,"cix":2,"bm":0,"ix":1,"mn":"ADBE Vector Group","hd":false}],"ip":26,"op":37,"st":26,"ct":1,"bm":0},{"ddd":0,"ind":4,"ty":4,"nm":"Shape Layer 2","sr":1,"ks":{"o":{"a":0,"k":100,"ix":11},"r":{"a":1,"k":[{"i":{"x":[0.833],"y":[0.833]},"o":{"x":[0.167],"y":[0.167]},"t":21,"s":[-46.674]},{"i":{"x":[0.833],"y":[0.833]},"o":{"x":[0.167],"y":[0.167]},"t":26,"s":[-65.536]},{"t":31,"s":[17.071]}],"ix":10},"p":{"a":1,"k":[{"i":{"x":0.833,"y":0.833},"o":{"x":0.167,"y":0.167},"t":21,"s":[112.272,152.75,0],"to":[-5.75,-43.167,0],"ti":[-2.75,55.167,0]},{"t":31,"s":[27.272,89.75,0]}],"ix":2,"l":2},"a":{"a":0,"k":[-93.728,-38.75,0],"ix":1,"l":2},"s":{"a":1,"k":[{"i":{"x":[0.667,0.667,0.667],"y":[1,1,1]},"o":{"x":[0.333,0.333,0.333],"y":[0,0,0]},"t":26,"s":[100,100,100]},{"t":31,"s":[0,0,100]}],"ix":6,"l":2}},"ao":0,"shapes":[{"ty":"gr","it":[{"ind":0,"ty":"sh","ix":1,"ks":{"a":0,"k":{"i":[[-12.5,13.25],[13.25,-12.75]],"o":[[11.25,11.5],[-13.25,-12.25]],"v":[[0,-21.75],[0,14.75]],"c":true},"ix":2},"nm":"Path 1","mn":"ADBE Vector Shape - Group","hd":false},{"ty":"fl","c":{"a":0,"k":[1,0.90588241278,0.415686304429,1],"ix":4},"o":{"a":0,"k":100,"ix":5},"r":1,"bm":0,"nm":"Fill 1","mn":"ADBE Vector Graphic - Fill","hd":false},{"ty":"tr","p":{"a":0,"k":[-93.5,-35.25],"ix":2},"a":{"a":0,"k":[0,0],"ix":1},"s":{"a":0,"k":[100,100],"ix":3},"r":{"a":0,"k":0,"ix":6},"o":{"a":0,"k":100,"ix":7},"sk":{"a":0,"k":0,"ix":4},"sa":{"a":0,"k":0,"ix":5},"nm":"Transform"}],"nm":"Ellipse 1","np":3,"cix":2,"bm":0,"ix":1,"mn":"ADBE Vector Group","hd":false}],"ip":21,"op":32,"st":21,"ct":1,"bm":0},{"ddd":0,"ind":5,"ty":0,"nm":"grey","refId":"comp_0","sr":1,"ks":{"o":{"a":0,"k":100,"ix":11},"r":{"a":0,"k":180,"ix":10},"p":{"a":0,"k":[240.75,65.5,0],"ix":2,"l":2},"a":{"a":0,"k":[10,10,0],"ix":1,"l":2},"s":{"a":0,"k":[-100,100,100],"ix":6,"l":2}},"ao":0,"w":20,"h":20,"ip":0,"op":91,"st":0,"bm":0},{"ddd":0,"ind":6,"ty":0,"nm":"grey","refId":"comp_0","sr":1,"ks":{"o":{"a":0,"k":100,"ix":11},"r":{"a":0,"k":180,"ix":10},"p":{"a":0,"k":[212.25,284.5,0],"ix":2,"l":2},"a":{"a":0,"k":[10,10,0],"ix":1,"l":2},"s":{"a":0,"k":[100,100,100],"ix":6,"l":2}},"ao":0,"w":20,"h":20,"ip":0,"op":91,"st":0,"bm":0},{"ddd":0,"ind":7,"ty":0,"nm":"grey","refId":"comp_0","sr":1,"ks":{"o":{"a":0,"k":100,"ix":11},"r":{"a":0,"k":180,"ix":10},"p":{"a":0,"k":[58.25,82.5,0],"ix":2,"l":2},"a":{"a":0,"k":[10,10,0],"ix":1,"l":2},"s":{"a":0,"k":[100,100,100],"ix":6,"l":2}},"ao":0,"w":20,"h":20,"ip":0,"op":91,"st":0,"bm":0},{"ddd":0,"ind":8,"ty":0,"nm":"grey","refId":"comp_0","sr":1,"ks":{"o":{"a":0,"k":100,"ix":11},"r":{"a":0,"k":0,"ix":10},"p":{"a":0,"k":[294.5,131.25,0],"ix":2,"l":2},"a":{"a":0,"k":[10,10,0],"ix":1,"l":2},"s":{"a":0,"k":[100,100,100],"ix":6,"l":2}},"ao":0,"w":20,"h":20,"ip":0,"op":91,"st":0,"bm":0},{"ddd":0,"ind":9,"ty":0,"nm":"grey","refId":"comp_0","sr":1,"ks":{"o":{"a":0,"k":100,"ix":11},"r":{"a":0,"k":0,"ix":10},"p":{"a":0,"k":[44,183.25,0],"ix":2,"l":2},"a":{"a":0,"k":[10,10,0],"ix":1,"l":2},"s":{"a":0,"k":[100,100,100],"ix":6,"l":2}},"ao":0,"w":20,"h":20,"ip":0,"op":91,"st":0,"bm":0},{"ddd":0,"ind":10,"ty":0,"nm":"purple","refId":"comp_1","sr":1,"ks":{"o":{"a":0,"k":100,"ix":11},"r":{"a":0,"k":-90,"ix":10},"p":{"a":0,"k":[265.5,272.5,0],"ix":2,"l":2},"a":{"a":0,"k":[25,25,0],"ix":1,"l":2},"s":{"a":0,"k":[100,100,100],"ix":6,"l":2}},"ao":0,"w":50,"h":50,"ip":0,"op":91,"st":0,"bm":0},{"ddd":0,"ind":11,"ty":0,"nm":"purple","refId":"comp_1","sr":1,"ks":{"o":{"a":0,"k":100,"ix":11},"r":{"a":0,"k":0,"ix":10},"p":{"a":0,"k":[111,48.5,0],"ix":2,"l":2},"a":{"a":0,"k":[25,25,0],"ix":1,"l":2},"s":{"a":0,"k":[100,100,100],"ix":6,"l":2}},"ao":0,"w":50,"h":50,"ip":0,"op":91,"st":0,"bm":0}],"markers":[]}